setup.cfg
setup.py
ml_first/ml_first.py
ml_first.egg-info/PKG-INFO
ml_first.egg-info/SOURCES.txt
ml_first.egg-info/dependency_links.txt
ml_first.egg-info/not-zip-safe
ml_first.egg-info/top_level.txt