Metadata-Version: 2.1
Name: ml-first
Version: 0.0
Summary: ml_first
Author-email: ilapronin0700@gmail.com
